respark/__init__.py
respark/runtime.py
respark/core/__init__.py
respark/core/numeric_types.py
respark/generate/__init__.py
respark/generate/generator.py
respark/layer_assurance/__init__.py
respark/layer_assurance/engine_reporting.py
respark/layer_assurance/engine_rules.py
respark/layer_assurance/inspect_privacy.py
respark/layer_assurance/inspect_structure.py
respark/plan/__init__.py
respark/plan/plan_types.py
respark/profile/__init__.py
respark/profile/profiling.py
respark/profile/column_profiles/__init__.py
respark/profile/column_profiles/base_column_profile.py
respark/profile/column_profiles/boolean_profile.py
respark/profile/column_profiles/datetime_profile.py
respark/profile/column_profiles/decimal_profile.py
respark/profile/column_profiles/fractional_profile.py
respark/profile/column_profiles/integral_profile.py
respark/profile/column_profiles/string_profile.py
respark/random/__init__.py
respark/random/hashing.py
respark/random/random_sampling.py
respark/random/rng.py
respark/random/seeding.py
respark/relationships/__init__.py
respark/relationships/dag.py
respark/relationships/relationship_types.py
respark/rules/__init__.py
respark/rules/registry.py
respark/rules/rule_types.py
respark/rules/generation_rules/__init__.py
respark/rules/generation_rules/core_generate_rules.py
respark/rules/generation_rules/generate_boolean.py
respark/rules/generation_rules/generate_datetime.py
respark/rules/generation_rules/generate_decimal.py
respark/rules/generation_rules/generate_fractional.py
respark/rules/generation_rules/generate_integral.py
respark/rules/generation_rules/generate_string.py
respark/rules/relational_rules/__init__.py
respark/rules/relational_rules/row_expression_rules.py
respark/rules/relational_rules/rule_switch.py
respark/rules/relational_rules/sampling_rules.py
respark/sampling/__init__.py
respark/sampling/index.py
respark/sampling/uniform.py
respark-0.0.14.dist-info/METADATA
respark-0.0.14.dist-info/WHEEL
respark-0.0.14.dist-info/licenses/LICENCE
respark-0.0.14.dist-info/RECORD
