Metadata-Version: 2.4
Name: respark
Version: 0.0.14
Summary: Generate privacy‑safe synthetic data from production Spark DataFrames
Project-URL: Source, https://github.com/dfe-analytical-services/respark
Author: Matthew Heath
License: The MIT License (MIT)
License-File: LICENCE
Classifier: Development Status :: 1 - Planning
Classifier: License :: OSI Approved :: MIT License
Classifier: Programming Language :: Python :: 3
Requires-Python: >=3.12
Provides-Extra: dev
Requires-Dist: coverage>=7.0; extra == 'dev'
Requires-Dist: pyspark<3.6,>=3.5; extra == 'dev'
Requires-Dist: pytest-cov>=4.1; extra == 'dev'
Requires-Dist: pytest>=7; extra == 'dev'
